{
    "instance_name": "9HR_6Q_100RQT_3q_bigTW_4",
    "solution_name": "9HR_6Q_100RQT_3q_bigTW_4_solution",
    "cost": 11887.0,
    "max_time": 12724.27578914047,
    "distance_travelled": 11867.190831346457,
    "costs_routes": {
        "robot_1": 0.0,
        "robot_2": 0.0,
        "robot_3": 0.0,
        "robot_4": 0.0,
        "robot_5": 9818.201736766916,
        "robot_6": 0.0,
        "robot_7": 0.0,
        "robot_8": 0.0,
        "robot_9": 2048.989094579541,
        "extra_robot_1": 0.0
    },
    "distances_routes": {
        "robot_1": 0.0,
        "robot_2": 0.0,
        "robot_3": 0.0,
        "robot_4": 0.0,
        "robot_5": 9818.201736766916,
        "robot_6": 0.0,
        "robot_7": 0.0,
        "robot_8": 0.0,
        "robot_9": 2048.989094579541,
        "extra_robot_1": 0.0
    },
    "complete_routes": {
        "robot_1": [
            {
                "node": "start_robot_1",
                "node_id": "depot_0",
                "arrival_time": 0.0,
                "departure_time": 12937.622658567143,
                "current_cost": 0.0,
                "current_load": 0,
                "distance_travelled": 0.0,
                "ongoing_request": []
            },
            {
                "node": "end_robot_1",
                "node_id": "depot_0",
                "arrival_time": 12937.622658567143,
                "departure_time": 12937.622658567143,
                "current_cost": 0.0,
                "current_load": 0,
                "distance_travelled": 0.0,
                "ongoing_request": []
            }
        ],
        "robot_2": [
            {
                "node": "start_robot_2",
                "node_id": "depot_0",
                "arrival_time": 0.0,
                "departure_time": 12937.622658567143,
                "current_cost": 0.0,
                "current_load": 0,
                "distance_travelled": 0.0,
                "ongoing_request": []
            },
            {
                "node": "end_robot_2",
                "node_id": "depot_0",
                "arrival_time": 12937.622658567143,
                "departure_time": 12937.622658567143,
                "current_cost": 0.0,
                "current_load": 0,
                "distance_travelled": 0.0,
                "ongoing_request": []
            }
        ],
        "robot_3": [
            {
                "node": "start_robot_3",
                "node_id": "depot_1",
                "arrival_time": 0.0,
                "departure_time": 12937.622658567143,
                "current_cost": 0.0,
                "current_load": 0,
                "distance_travelled": 0.0,
                "ongoing_request": []
            },
            {
                "node": "end_robot_3",
                "node_id": "depot_1",
                "arrival_time": 12937.622658567143,
                "departure_time": 12937.622658567143,
                "current_cost": 0.0,
                "current_load": 0,
                "distance_travelled": 0.0,
                "ongoing_request": []
            }
        ],
        "robot_4": [
            {
                "node": "start_robot_4",
                "node_id": "depot_0",
                "arrival_time": 0.0,
                "departure_time": 12937.622658567143,
                "current_cost": 0.0,
                "current_load": 0,
                "distance_travelled": 0.0,
                "ongoing_request": []
            },
            {
                "node": "end_robot_4",
                "node_id": "depot_0",
                "arrival_time": 12937.622658567143,
                "departure_time": 12937.622658567143,
                "current_cost": 0.0,
                "current_load": 0,
                "distance_travelled": 0.0,
                "ongoing_request": []
            }
        ],
        "robot_5": [
            {
                "node": "start_robot_5",
                "node_id": "depot_0",
                "arrival_time": 0.0,
                "departure_time": 322.69735037443047,
                "current_cost": 0.0,
                "current_load": 0,
                "distance_travelled": 0.0,
                "ongoing_request": []
            },
            {
                "node": "pickup_request_4",
                "node_id": "f_15",
                "arrival_time": 335.7357551848358,
                "departure_time": 336.7357551848358,
                "current_cost": 13.038404810405298,
                "current_load": 3,
                "distance_travelled": 13.038404810405298,
                "ongoing_request": [
                    "request_4"
                ]
            },
            {
                "node": "delivery_request_4",
                "node_id": "truck_1",
                "arrival_time": 408.2409997477348,
                "departure_time": 483.0213856807375,
                "current_cost": 84.54364937330432,
                "current_load": 0,
                "distance_travelled": 84.54364937330432,
                "ongoing_request": []
            },
            {
                "node": "pickup_request_5",
                "node_id": "f_6",
                "arrival_time": 577.81590028997,
                "departure_time": 578.81590028997,
                "current_cost": 179.33816398253686,
                "current_load": 3,
                "distance_travelled": 179.33816398253686,
                "ongoing_request": [
                    "request_5"
                ]
            },
            {
                "node": "pickup_request_6",
                "node_id": "f_40",
                "arrival_time": 649.6749152421976,
                "departure_time": 650.6749152421976,
                "current_cost": 250.19717893476434,
                "current_load": 6,
                "distance_travelled": 250.19717893476434,
                "ongoing_request": [
                    "request_5",
                    "request_6"
                ]
            },
            {
                "node": "delivery_request_5",
                "node_id": "truck_0",
                "arrival_time": 693.9992732870666,
                "departure_time": 694.9992732870666,
                "current_cost": 293.52153697963325,
                "current_load": 3,
                "distance_travelled": 293.52153697963325,
                "ongoing_request": [
                    "request_6"
                ]
            },
            {
                "node": "delivery_request_6",
                "node_id": "truck_0",
                "arrival_time": 694.9992732870666,
                "departure_time": 695.9992732870666,
                "current_cost": 293.52153697963325,
                "current_load": 0,
                "distance_travelled": 293.52153697963325,
                "ongoing_request": []
            },
            {
                "node": "pickup_request_7",
                "node_id": "f_91",
                "arrival_time": 730.7123832024861,
                "departure_time": 731.7123832024861,
                "current_cost": 328.23464689505283,
                "current_load": 3,
                "distance_travelled": 328.23464689505283,
                "ongoing_request": [
                    "request_7"
                ]
            },
            {
                "node": "pickup_request_8",
                "node_id": "f_80",
                "arrival_time": 779.0938141644147,
                "departure_time": 780.0938141644147,
                "current_cost": 375.61607785698135,
                "current_load": 6,
                "distance_travelled": 375.61607785698135,
                "ongoing_request": [
                    "request_7",
                    "request_8"
                ]
            },
            {
                "node": "delivery_request_7",
                "node_id": "truck_0",
                "arrival_time": 820.0938141644147,
                "departure_time": 821.0938141644147,
                "current_cost": 415.61607785698135,
                "current_load": 3,
                "distance_travelled": 415.61607785698135,
                "ongoing_request": [
                    "request_8"
                ]
            },
            {
                "node": "delivery_request_8",
                "node_id": "truck_0",
                "arrival_time": 821.0938141644147,
                "departure_time": 841.2383079634608,
                "current_cost": 415.61607785698135,
                "current_load": 0,
                "distance_travelled": 415.61607785698135,
                "ongoing_request": []
            },
            {
                "node": "pickup_request_9",
                "node_id": "f_76",
                "arrival_time": 922.7306388909781,
                "departure_time": 923.7306388909781,
                "current_cost": 497.1084087844987,
                "current_load": 3,
                "distance_travelled": 497.1084087844987,
                "ongoing_request": [
                    "request_9"
                ]
            },
            {
                "node": "delivery_request_9",
                "node_id": "truck_2",
                "arrival_time": 956.3802943256071,
                "departure_time": 957.3802943256071,
                "current_cost": 529.7580642191277,
                "current_load": 0,
                "distance_travelled": 529.7580642191277,
                "ongoing_request": []
            },
            {
                "node": "pickup_request_10",
                "node_id": "f_22",
                "arrival_time": 1016.5157320934971,
                "departure_time": 1017.5157320934971,
                "current_cost": 588.8935019870178,
                "current_load": 3,
                "distance_travelled": 588.8935019870178,
                "ongoing_request": [
                    "request_10"
                ]
            },
            {
                "node": "delivery_request_10",
                "node_id": "truck_0",
                "arrival_time": 1041.5989212510817,
                "departure_time": 1075.983203736216,
                "current_cost": 612.9766911446023,
                "current_load": 0,
                "distance_travelled": 612.9766911446023,
                "ongoing_request": []
            },
            {
                "node": "pickup_request_11",
                "node_id": "f_53",
                "arrival_time": 1149.7463381598561,
                "departure_time": 1150.7463381598561,
                "current_cost": 686.7398255682424,
                "current_load": 3,
                "distance_travelled": 686.7398255682424,
                "ongoing_request": [
                    "request_11"
                ]
            },
            {
                "node": "delivery_request_11",
                "node_id": "truck_0",
                "arrival_time": 1224.5094725834963,
                "departure_time": 1225.5094725834963,
                "current_cost": 760.5029599918826,
                "current_load": 0,
                "distance_travelled": 760.5029599918826,
                "ongoing_request": []
            },
            {
                "node": "pickup_request_12",
                "node_id": "f_27",
                "arrival_time": 1323.0389553053892,
                "departure_time": 1324.0389553053892,
                "current_cost": 858.0324427137755,
                "current_load": 3,
                "distance_travelled": 858.0324427137755,
                "ongoing_request": [
                    "request_12"
                ]
            },
            {
                "node": "delivery_request_12",
                "node_id": "truck_1",
                "arrival_time": 1341.7590004520584,
                "departure_time": 1371.5599852670018,
                "current_cost": 875.7524878604448,
                "current_load": 0,
                "distance_travelled": 875.7524878604448,
                "ongoing_request": []
            },
            {
                "node": "pickup_request_13",
                "node_id": "f_17",
                "arrival_time": 1455.2319638500376,
                "departure_time": 1456.2319638500376,
                "current_cost": 959.4244664434806,
                "current_load": 3,
                "distance_travelled": 959.4244664434806,
                "ongoing_request": [
                    "request_13"
                ]
            },
            {
                "node": "delivery_request_13",
                "node_id": "truck_0",
                "arrival_time": 1548.8872389292255,
                "departure_time": 1613.292185729141,
                "current_cost": 1052.0797415226687,
                "current_load": 0,
                "distance_travelled": 1052.0797415226687,
                "ongoing_request": []
            },
            {
                "node": "pickup_request_15",
                "node_id": "f_21",
                "arrival_time": 1702.7349048291326,
                "departure_time": 1703.7349048291326,
                "current_cost": 1141.5224606226602,
                "current_load": 3,
                "distance_travelled": 1141.5224606226602,
                "ongoing_request": [
                    "request_15"
                ]
            },
            {
                "node": "delivery_request_15",
                "node_id": "truck_0",
                "arrival_time": 1793.1776239291241,
                "departure_time": 1794.1776239291241,
                "current_cost": 1230.9651797226518,
                "current_load": 0,
                "distance_travelled": 1230.9651797226518,
                "ongoing_request": []
            },
            {
                "node": "pickup_request_16",
                "node_id": "f_92",
                "arrival_time": 1840.2753462155886,
                "departure_time": 1841.2753462155886,
                "current_cost": 1277.0629020091162,
                "current_load": 3,
                "distance_travelled": 1277.0629020091162,
                "ongoing_request": [
                    "request_16"
                ]
            },
            {
                "node": "delivery_request_16",
                "node_id": "truck_2",
                "arrival_time": 1883.1561293983325,
                "departure_time": 1964.9630939870758,
                "current_cost": 1318.9436851918601,
                "current_load": 0,
                "distance_travelled": 1318.9436851918601,
                "ongoing_request": []
            },
            {
                "node": "pickup_request_18",
                "node_id": "f_80",
                "arrival_time": 1983.6446356793451,
                "departure_time": 1984.6446356793451,
                "current_cost": 1337.6252268841295,
                "current_load": 3,
                "distance_travelled": 1337.6252268841295,
                "ongoing_request": [
                    "request_18"
                ]
            },
            {
                "node": "delivery_request_18",
                "node_id": "truck_1",
                "arrival_time": 2044.3271289248523,
                "departure_time": 2104.478742121743,
                "current_cost": 1397.3077201296367,
                "current_load": 0,
                "distance_travelled": 1397.3077201296367,
                "ongoing_request": []
            },
            {
                "node": "pickup_request_19",
                "node_id": "f_80",
                "arrival_time": 2164.16123536725,
                "departure_time": 2165.16123536725,
                "current_cost": 1456.9902133751439,
                "current_load": 3,
                "distance_travelled": 1456.9902133751439,
                "ongoing_request": [
                    "request_19"
                ]
            },
            {
                "node": "delivery_request_19",
                "node_id": "truck_3",
                "arrival_time": 2242.99439025641,
                "departure_time": 2293.9124246354468,
                "current_cost": 1534.823368264304,
                "current_load": 0,
                "distance_travelled": 1534.823368264304,
                "ongoing_request": []
            },
            {
                "node": "pickup_request_20",
                "node_id": "f_19",
                "arrival_time": 2389.6673200716596,
                "departure_time": 2390.6673200716596,
                "current_cost": 1630.5782637005166,
                "current_load": 3,
                "distance_travelled": 1630.5782637005166,
                "ongoing_request": [
                    "request_20"
                ]
            },
            {
                "node": "delivery_request_20",
                "node_id": "truck_1",
                "arrival_time": 2482.346107149151,
                "departure_time": 2483.346107149151,
                "current_cost": 1722.2570507780079,
                "current_load": 0,
                "distance_travelled": 1722.2570507780079,
                "ongoing_request": []
            },
            {
                "node": "pickup_request_21",
                "node_id": "f_30",
                "arrival_time": 2495.008010938842,
                "departure_time": 2496.008010938842,
                "current_cost": 1733.9189545676984,
                "current_load": 3,
                "distance_travelled": 1733.9189545676984,
                "ongoing_request": [
                    "request_21"
                ]
            },
            {
                "node": "delivery_request_21",
                "node_id": "truck_0",
                "arrival_time": 2585.0585583824145,
                "departure_time": 2586.0585583824145,
                "current_cost": 1822.969502011271,
                "current_load": 0,
                "distance_travelled": 1822.969502011271,
                "ongoing_request": []
            },
            {
                "node": "pickup_request_22",
                "node_id": "f_62",
                "arrival_time": 2625.8706168572035,
                "departure_time": 2626.8706168572035,
                "current_cost": 1862.7815604860598,
                "current_load": 3,
                "distance_travelled": 1862.7815604860598,
                "ongoing_request": [
                    "request_22"
                ]
            },
            {
                "node": "delivery_request_22",
                "node_id": "truck_1",
                "arrival_time": 2695.0248537027583,
                "departure_time": 2696.0248537027583,
                "current_cost": 1930.9357973316148,
                "current_load": 0,
                "distance_travelled": 1930.9357973316148,
                "ongoing_request": []
            },
            {
                "node": "pickup_request_23",
                "node_id": "f_73",
                "arrival_time": 2718.850278123785,
                "departure_time": 2719.850278123785,
                "current_cost": 1953.7612217526414,
                "current_load": 3,
                "distance_travelled": 1953.7612217526414,
                "ongoing_request": [
                    "request_23"
                ]
            },
            {
                "node": "delivery_request_23",
                "node_id": "truck_0",
                "arrival_time": 2812.505553202973,
                "departure_time": 2813.505553202973,
                "current_cost": 2046.4164968318294,
                "current_load": 0,
                "distance_travelled": 2046.4164968318294,
                "ongoing_request": []
            },
            {
                "node": "pickup_request_24",
                "node_id": "f_85",
                "arrival_time": 2846.6416362545347,
                "departure_time": 2847.6416362545347,
                "current_cost": 2079.552579883391,
                "current_load": 3,
                "distance_travelled": 2079.552579883391,
                "ongoing_request": [
                    "request_24"
                ]
            },
            {
                "node": "delivery_request_24",
                "node_id": "truck_1",
                "arrival_time": 2952.4271314339726,
                "departure_time": 2953.4271314339726,
                "current_cost": 2184.338075062829,
                "current_load": 0,
                "distance_travelled": 2184.338075062829,
                "ongoing_request": []
            },
            {
                "node": "pickup_request_25",
                "node_id": "f_88",
                "arrival_time": 2995.971226206338,
                "departure_time": 2996.971226206338,
                "current_cost": 2226.8821698351944,
                "current_load": 3,
                "distance_travelled": 2226.8821698351944,
                "ongoing_request": [
                    "request_25"
                ]
            },
            {
                "node": "delivery_request_25",
                "node_id": "truck_0",
                "arrival_time": 3060.1218398217256,
                "departure_time": 3186.855448064159,
                "current_cost": 2290.032783450582,
                "current_load": 0,
                "distance_travelled": 2290.032783450582,
                "ongoing_request": []
            },
            {
                "node": "pickup_request_27",
                "node_id": "f_60",
                "arrival_time": 3215.0157037448166,
                "departure_time": 3216.0157037448166,
                "current_cost": 2318.1930391312394,
                "current_load": 3,
                "distance_travelled": 2318.1930391312394,
                "ongoing_request": [
                    "request_27"
                ]
            },
            {
                "node": "delivery_request_27",
                "node_id": "truck_3",
                "arrival_time": 3308.735712372944,
                "departure_time": 3337.990823740973,
                "current_cost": 2410.9130477593667,
                "current_load": 0,
                "distance_travelled": 2410.9130477593667,
                "ongoing_request": []
            },
            {
                "node": "pickup_request_28",
                "node_id": "f_67",
                "arrival_time": 3406.6712430757443,
                "departure_time": 3407.6712430757443,
                "current_cost": 2479.593467094138,
                "current_load": 3,
                "distance_travelled": 2479.593467094138,
                "ongoing_request": [
                    "request_28"
                ]
            },
            {
                "node": "delivery_request_28",
                "node_id": "truck_1",
                "arrival_time": 3488.126199417787,
                "departure_time": 3489.126199417787,
                "current_cost": 2560.0484234361807,
                "current_load": 0,
                "distance_travelled": 2560.0484234361807,
                "ongoing_request": []
            },
            {
                "node": "pickup_request_29",
                "node_id": "f_50",
                "arrival_time": 3554.43316688681,
                "departure_time": 3555.43316688681,
                "current_cost": 2625.3553909052034,
                "current_load": 3,
                "distance_travelled": 2625.3553909052034,
                "ongoing_request": [
                    "request_29"
                ]
            },
            {
                "node": "delivery_request_29",
                "node_id": "truck_0",
                "arrival_time": 3599.716346537779,
                "departure_time": 3627.908224523189,
                "current_cost": 2669.6385705561725,
                "current_load": 0,
                "distance_travelled": 2669.6385705561725,
                "ongoing_request": []
            },
            {
                "node": "pickup_request_30",
                "node_id": "f_17",
                "arrival_time": 3720.563499602377,
                "departure_time": 3721.563499602377,
                "current_cost": 2762.2938456353604,
                "current_load": 3,
                "distance_travelled": 2762.2938456353604,
                "ongoing_request": [
                    "request_30"
                ]
            },
            {
                "node": "delivery_request_30",
                "node_id": "truck_1",
                "arrival_time": 3805.235478185413,
                "departure_time": 3806.235478185413,
                "current_cost": 2845.9658242183964,
                "current_load": 0,
                "distance_travelled": 2845.9658242183964,
                "ongoing_request": []
            },
            {
                "node": "pickup_request_31",
                "node_id": "f_47",
                "arrival_time": 3904.1435983798074,
                "departure_time": 3905.1435983798074,
                "current_cost": 2943.873944412791,
                "current_load": 3,
                "distance_travelled": 2943.873944412791,
                "ongoing_request": [
                    "request_31"
                ]
            },
            {
                "node": "delivery_request_31",
                "node_id": "truck_0",
                "arrival_time": 3954.539954520721,
                "departure_time": 4459.477059047355,
                "current_cost": 2993.2703005537046,
                "current_load": 0,
                "distance_travelled": 2993.2703005537046,
                "ongoing_request": []
            },
            {
                "node": "pickup_request_35",
                "node_id": "f_54",
                "arrival_time": 4525.241791237185,
                "departure_time": 4526.241791237185,
                "current_cost": 3059.035032743534,
                "current_load": 3,
                "distance_travelled": 3059.035032743534,
                "ongoing_request": [
                    "request_35"
                ]
            },
            {
                "node": "delivery_request_35",
                "node_id": "truck_0",
                "arrival_time": 4592.006523427014,
                "departure_time": 4639.578153934502,
                "current_cost": 3124.7997649333633,
                "current_load": 0,
                "distance_travelled": 3124.7997649333633,
                "ongoing_request": []
            },
            {
                "node": "pickup_request_36",
                "node_id": "f_30",
                "arrival_time": 4728.628701378075,
                "departure_time": 4729.628701378075,
                "current_cost": 3213.850312376936,
                "current_load": 3,
                "distance_travelled": 3213.850312376936,
                "ongoing_request": [
                    "request_36"
                ]
            },
            {
                "node": "delivery_request_36",
                "node_id": "truck_0",
                "arrival_time": 4818.679248821648,
                "departure_time": 4887.794660375868,
                "current_cost": 3302.9008598205087,
                "current_load": 0,
                "distance_travelled": 3302.9008598205087,
                "ongoing_request": []
            },
            {
                "node": "pickup_request_38",
                "node_id": "f_57",
                "arrival_time": 4948.92566723818,
                "departure_time": 4949.92566723818,
                "current_cost": 3364.0318666828202,
                "current_load": 3,
                "distance_travelled": 3364.0318666828202,
                "ongoing_request": [
                    "request_38"
                ]
            },
            {
                "node": "delivery_request_38",
                "node_id": "truck_2",
                "arrival_time": 4960.971028255367,
                "departure_time": 4961.971028255367,
                "current_cost": 3375.0772277000074,
                "current_load": 0,
                "distance_travelled": 3375.0772277000074,
                "ongoing_request": []
            },
            {
                "node": "pickup_request_39",
                "node_id": "f_88",
                "arrival_time": 4970.033286003665,
                "departure_time": 4971.033286003665,
                "current_cost": 3383.139485448306,
                "current_load": 3,
                "distance_travelled": 3383.139485448306,
                "ongoing_request": [
                    "request_39"
                ]
            },
            {
                "node": "delivery_request_39",
                "node_id": "truck_3",
                "arrival_time": 5024.940613891439,
                "departure_time": 5141.833820094915,
                "current_cost": 3437.04681333608,
                "current_load": 0,
                "distance_travelled": 3437.04681333608,
                "ongoing_request": []
            },
            {
                "node": "pickup_request_40",
                "node_id": "f_84",
                "arrival_time": 5242.536352337158,
                "departure_time": 5243.536352337158,
                "current_cost": 3537.7493455783233,
                "current_load": 3,
                "distance_travelled": 3537.7493455783233,
                "ongoing_request": [
                    "request_40"
                ]
            },
            {
                "node": "delivery_request_40",
                "node_id": "truck_1",
                "arrival_time": 5330.903394177889,
                "departure_time": 5331.903394177889,
                "current_cost": 3625.1163874190543,
                "current_load": 0,
                "distance_travelled": 3625.1163874190543,
                "ongoing_request": []
            },
            {
                "node": "pickup_request_41",
                "node_id": "f_50",
                "arrival_time": 5397.210361646912,
                "departure_time": 5398.210361646912,
                "current_cost": 3690.423354888077,
                "current_load": 3,
                "distance_travelled": 3690.423354888077,
                "ongoing_request": [
                    "request_41"
                ]
            },
            {
                "node": "pickup_request_42",
                "node_id": "f_41",
                "arrival_time": 5429.081059727779,
                "departure_time": 5430.081059727779,
                "current_cost": 3721.294052968943,
                "current_load": 6,
                "distance_travelled": 3721.294052968943,
                "ongoing_request": [
                    "request_41",
                    "request_42"
                ]
            },
            {
                "node": "delivery_request_41",
                "node_id": "truck_3",
                "arrival_time": 5474.488266350128,
                "departure_time": 5475.488266350128,
                "current_cost": 3765.701259591292,
                "current_load": 3,
                "distance_travelled": 3765.701259591292,
                "ongoing_request": [
                    "request_42"
                ]
            },
            {
                "node": "delivery_request_42",
                "node_id": "truck_2",
                "arrival_time": 5537.34126209352,
                "departure_time": 5538.34126209352,
                "current_cost": 3827.554255334684,
                "current_load": 0,
                "distance_travelled": 3827.554255334684,
                "ongoing_request": []
            },
            {
                "node": "pickup_request_43",
                "node_id": "f_59",
                "arrival_time": 5555.545912627605,
                "departure_time": 5556.545912627605,
                "current_cost": 3844.7589058687695,
                "current_load": 3,
                "distance_travelled": 3844.7589058687695,
                "ongoing_request": [
                    "request_43"
                ]
            },
            {
                "node": "pickup_request_44",
                "node_id": "f_43",
                "arrival_time": 5569.58431743801,
                "departure_time": 5570.58431743801,
                "current_cost": 3857.7973106791746,
                "current_load": 6,
                "distance_travelled": 3857.7973106791746,
                "ongoing_request": [
                    "request_43",
                    "request_44"
                ]
            },
            {
                "node": "delivery_request_44",
                "node_id": "truck_2",
                "arrival_time": 5598.043377873501,
                "departure_time": 5599.043377873501,
                "current_cost": 3885.2563711146668,
                "current_load": 3,
                "distance_travelled": 3885.2563711146668,
                "ongoing_request": [
                    "request_43"
                ]
            },
            {
                "node": "delivery_request_43",
                "node_id": "truck_3",
                "arrival_time": 5660.8963736168935,
                "departure_time": 5661.8963736168935,
                "current_cost": 3947.109366858059,
                "current_load": 0,
                "distance_travelled": 3947.109366858059,
                "ongoing_request": []
            },
            {
                "node": "pickup_request_45",
                "node_id": "f_16",
                "arrival_time": 5744.030410410418,
                "departure_time": 5745.030410410418,
                "current_cost": 4029.2434036515833,
                "current_load": 3,
                "distance_travelled": 4029.2434036515833,
                "ongoing_request": [
                    "request_45"
                ]
            },
            {
                "node": "delivery_request_45",
                "node_id": "truck_1",
                "arrival_time": 5802.039181665375,
                "departure_time": 5803.039181665375,
                "current_cost": 4086.2521749065404,
                "current_load": 0,
                "distance_travelled": 4086.2521749065404,
                "ongoing_request": []
            },
            {
                "node": "pickup_request_46",
                "node_id": "f_30",
                "arrival_time": 5814.701085455065,
                "departure_time": 5815.701085455065,
                "current_cost": 4097.914078696231,
                "current_load": 3,
                "distance_travelled": 4097.914078696231,
                "ongoing_request": [
                    "request_46"
                ]
            },
            {
                "node": "delivery_request_46",
                "node_id": "truck_0",
                "arrival_time": 5904.7516328986385,
                "departure_time": 5905.7516328986385,
                "current_cost": 4186.964626139804,
                "current_load": 0,
                "distance_travelled": 4186.964626139804,
                "ongoing_request": []
            },
            {
                "node": "pickup_request_47",
                "node_id": "f_81",
                "arrival_time": 5972.818763447068,
                "departure_time": 5973.818763447068,
                "current_cost": 4254.031756688233,
                "current_load": 3,
                "distance_travelled": 4254.031756688233,
                "ongoing_request": [
                    "request_47"
                ]
            },
            {
                "node": "delivery_request_47",
                "node_id": "truck_0",
                "arrival_time": 6040.885893995497,
                "departure_time": 6041.885893995497,
                "current_cost": 4321.098887236662,
                "current_load": 0,
                "distance_travelled": 4321.098887236662,
                "ongoing_request": []
            },
            {
                "node": "pickup_request_48",
                "node_id": "f_4",
                "arrival_time": 6096.116881447322,
                "departure_time": 6097.116881447322,
                "current_cost": 4375.3298746884875,
                "current_load": 3,
                "distance_travelled": 4375.3298746884875,
                "ongoing_request": [
                    "request_48"
                ]
            },
            {
                "node": "delivery_request_48",
                "node_id": "truck_3",
                "arrival_time": 6189.1223160694135,
                "departure_time": 6203.701932565183,
                "current_cost": 4467.335309310579,
                "current_load": 0,
                "distance_travelled": 4467.335309310579,
                "ongoing_request": []
            },
            {
                "node": "pickup_request_49",
                "node_id": "f_4",
                "arrival_time": 6295.707367187274,
                "departure_time": 6296.707367187274,
                "current_cost": 4559.34074393267,
                "current_load": 3,
                "distance_travelled": 4559.34074393267,
                "ongoing_request": [
                    "request_49"
                ]
            },
            {
                "node": "delivery_request_49",
                "node_id": "truck_3",
                "arrival_time": 6388.712801809365,
                "departure_time": 6389.712801809365,
                "current_cost": 4651.3461785547615,
                "current_load": 0,
                "distance_travelled": 4651.3461785547615,
                "ongoing_request": []
            },
            {
                "node": "pickup_request_50",
                "node_id": "f_62",
                "arrival_time": 6460.543586077224,
                "departure_time": 6461.543586077224,
                "current_cost": 4722.17696282262,
                "current_load": 3,
                "distance_travelled": 4722.17696282262,
                "ongoing_request": [
                    "request_50"
                ]
            },
            {
                "node": "delivery_request_50",
                "node_id": "truck_3",
                "arrival_time": 6532.374370345083,
                "departure_time": 6533.374370345083,
                "current_cost": 4793.007747090479,
                "current_load": 0,
                "distance_travelled": 4793.007747090479,
                "ongoing_request": []
            },
            {
                "node": "pickup_request_51",
                "node_id": "f_28",
                "arrival_time": 6611.16897170019,
                "departure_time": 6612.16897170019,
                "current_cost": 4870.802348445586,
                "current_load": 3,
                "distance_travelled": 4870.802348445586,
                "ongoing_request": [
                    "request_51"
                ]
            },
            {
                "node": "pickup_request_52",
                "node_id": "f_53",
                "arrival_time": 6647.679533509319,
                "departure_time": 6648.679533509319,
                "current_cost": 4906.3129102547155,
                "current_load": 6,
                "distance_travelled": 4906.3129102547155,
                "ongoing_request": [
                    "request_51",
                    "request_52"
                ]
            },
            {
                "node": "delivery_request_51",
                "node_id": "truck_1",
                "arrival_time": 6678.762751422302,
                "departure_time": 6679.762751422302,
                "current_cost": 4936.396128167698,
                "current_load": 3,
                "distance_travelled": 4936.396128167698,
                "ongoing_request": [
                    "request_52"
                ]
            },
            {
                "node": "delivery_request_52",
                "node_id": "truck_2",
                "arrival_time": 6723.088315143898,
                "departure_time": 6847.680055032828,
                "current_cost": 4979.721691889295,
                "current_load": 0,
                "distance_travelled": 4979.721691889295,
                "ongoing_request": []
            },
            {
                "node": "pickup_request_54",
                "node_id": "f_34",
                "arrival_time": 6920.597816929365,
                "departure_time": 6921.597816929365,
                "current_cost": 5052.639453785831,
                "current_load": 3,
                "distance_travelled": 5052.639453785831,
                "ongoing_request": [
                    "request_54"
                ]
            },
            {
                "node": "delivery_request_54",
                "node_id": "truck_2",
                "arrival_time": 6994.515578825902,
                "departure_time": 6995.515578825902,
                "current_cost": 5125.557215682368,
                "current_load": 0,
                "distance_travelled": 5125.557215682368,
                "ongoing_request": []
            },
            {
                "node": "pickup_request_55",
                "node_id": "f_99",
                "arrival_time": 7017.65152244708,
                "departure_time": 7018.65152244708,
                "current_cost": 5147.693159303547,
                "current_load": 3,
                "distance_travelled": 5147.693159303547,
                "ongoing_request": [
                    "request_55"
                ]
            },
            {
                "node": "delivery_request_55",
                "node_id": "truck_3",
                "arrival_time": 7076.522067632001,
                "departure_time": 7077.522067632001,
                "current_cost": 5205.563704488468,
                "current_load": 0,
                "distance_travelled": 5205.563704488468,
                "ongoing_request": []
            },
            {
                "node": "pickup_request_56",
                "node_id": "f_19",
                "arrival_time": 7173.276963068214,
                "departure_time": 7174.276963068214,
                "current_cost": 5301.318599924681,
                "current_load": 3,
                "distance_travelled": 5301.318599924681,
                "ongoing_request": [
                    "request_56"
                ]
            },
            {
                "node": "pickup_request_57",
                "node_id": "f_41",
                "arrival_time": 7229.094843362877,
                "departure_time": 7230.094843362877,
                "current_cost": 5356.136480219344,
                "current_load": 6,
                "distance_travelled": 5356.136480219344,
                "ongoing_request": [
                    "request_56",
                    "request_57"
                ]
            },
            {
                "node": "delivery_request_56",
                "node_id": "truck_2",
                "arrival_time": 7272.39141532799,
                "departure_time": 7273.39141532799,
                "current_cost": 5398.433052184457,
                "current_load": 3,
                "distance_travelled": 5398.433052184457,
                "ongoing_request": [
                    "request_57"
                ]
            },
            {
                "node": "delivery_request_57",
                "node_id": "truck_2",
                "arrival_time": 7273.39141532799,
                "departure_time": 7274.39141532799,
                "current_cost": 5398.433052184457,
                "current_load": 0,
                "distance_travelled": 5398.433052184457,
                "ongoing_request": []
            },
            {
                "node": "pickup_request_58",
                "node_id": "f_20",
                "arrival_time": 7301.465388069352,
                "departure_time": 7302.465388069352,
                "current_cost": 5425.507024925819,
                "current_load": 3,
                "distance_travelled": 5425.507024925819,
                "ongoing_request": [
                    "request_58"
                ]
            },
            {
                "node": "delivery_request_58",
                "node_id": "truck_2",
                "arrival_time": 7329.539360810714,
                "departure_time": 7345.991656225829,
                "current_cost": 5452.580997667181,
                "current_load": 0,
                "distance_travelled": 5452.580997667181,
                "ongoing_request": []
            },
            {
                "node": "pickup_request_59",
                "node_id": "f_63",
                "arrival_time": 7387.18631607392,
                "departure_time": 7388.18631607392,
                "current_cost": 5493.7756575152725,
                "current_load": 3,
                "distance_travelled": 5493.7756575152725,
                "ongoing_request": [
                    "request_59"
                ]
            },
            {
                "node": "delivery_request_59",
                "node_id": "truck_1",
                "arrival_time": 7472.1386835211815,
                "departure_time": 7473.1386835211815,
                "current_cost": 5577.728024962534,
                "current_load": 0,
                "distance_travelled": 5577.728024962534,
                "ongoing_request": []
            },
            {
                "node": "pickup_request_60",
                "node_id": "f_27",
                "arrival_time": 7490.858728667851,
                "departure_time": 7491.858728667851,
                "current_cost": 5595.448070109203,
                "current_load": 3,
                "distance_travelled": 5595.448070109203,
                "ongoing_request": [
                    "request_60"
                ]
            },
            {
                "node": "delivery_request_60",
                "node_id": "truck_3",
                "arrival_time": 7570.91567017206,
                "departure_time": 7699.939203134532,
                "current_cost": 5674.5050116134125,
                "current_load": 0,
                "distance_travelled": 5674.5050116134125,
                "ongoing_request": []
            },
            {
                "node": "pickup_request_62",
                "node_id": "f_74",
                "arrival_time": 7703.939203134532,
                "departure_time": 7704.939203134532,
                "current_cost": 5678.5050116134125,
                "current_load": 3,
                "distance_travelled": 5678.5050116134125,
                "ongoing_request": [
                    "request_62"
                ]
            },
            {
                "node": "delivery_request_62",
                "node_id": "truck_0",
                "arrival_time": 7811.98125094753,
                "departure_time": 7814.323854000264,
                "current_cost": 5785.54705942641,
                "current_load": 0,
                "distance_travelled": 5785.54705942641,
                "ongoing_request": []
            },
            {
                "node": "pickup_request_63",
                "node_id": "f_32",
                "arrival_time": 7843.323854000264,
                "departure_time": 7844.323854000264,
                "current_cost": 5814.54705942641,
                "current_load": 3,
                "distance_travelled": 5814.54705942641,
                "ongoing_request": [
                    "request_63"
                ]
            },
            {
                "node": "delivery_request_63",
                "node_id": "truck_3",
                "arrival_time": 7927.708504865996,
                "departure_time": 8141.657532658937,
                "current_cost": 5897.931710292141,
                "current_load": 0,
                "distance_travelled": 5897.931710292141,
                "ongoing_request": []
            },
            {
                "node": "pickup_request_65",
                "node_id": "f_90",
                "arrival_time": 8219.683169471462,
                "departure_time": 8220.683169471462,
                "current_cost": 5975.957347104666,
                "current_load": 3,
                "distance_travelled": 5975.957347104666,
                "ongoing_request": [
                    "request_65"
                ]
            },
            {
                "node": "delivery_request_65",
                "node_id": "truck_2",
                "arrival_time": 8271.486712654983,
                "departure_time": 8272.486712654983,
                "current_cost": 6026.760890288188,
                "current_load": 0,
                "distance_travelled": 6026.760890288188,
                "ongoing_request": []
            },
            {
                "node": "pickup_request_66",
                "node_id": "f_10",
                "arrival_time": 8284.65223771558,
                "departure_time": 8285.65223771558,
                "current_cost": 6038.926415348785,
                "current_load": 3,
                "distance_travelled": 6038.926415348785,
                "ongoing_request": [
                    "request_66"
                ]
            },
            {
                "node": "delivery_request_66",
                "node_id": "truck_0",
                "arrival_time": 8355.716493937993,
                "departure_time": 8358.48396518745,
                "current_cost": 6108.990671571199,
                "current_load": 0,
                "distance_travelled": 6108.990671571199,
                "ongoing_request": []
            },
            {
                "node": "pickup_request_67",
                "node_id": "f_6",
                "arrival_time": 8422.013485884525,
                "departure_time": 8423.013485884525,
                "current_cost": 6172.520192268273,
                "current_load": 3,
                "distance_travelled": 6172.520192268273,
                "ongoing_request": [
                    "request_67"
                ]
            },
            {
                "node": "delivery_request_67",
                "node_id": "truck_3",
                "arrival_time": 8490.080616432953,
                "departure_time": 8491.080616432953,
                "current_cost": 6239.587322816702,
                "current_load": 0,
                "distance_travelled": 6239.587322816702,
                "ongoing_request": []
            },
            {
                "node": "pickup_request_68",
                "node_id": "f_22",
                "arrival_time": 8590.408356767666,
                "departure_time": 8591.408356767666,
                "current_cost": 6338.915063151414,
                "current_load": 3,
                "distance_travelled": 6338.915063151414,
                "ongoing_request": [
                    "request_68"
                ]
            },
            {
                "node": "delivery_request_68",
                "node_id": "truck_0",
                "arrival_time": 8615.491545925252,
                "departure_time": 8642.573660554004,
                "current_cost": 6362.998252308998,
                "current_load": 0,
                "distance_travelled": 6362.998252308998,
                "ongoing_request": []
            },
            {
                "node": "pickup_request_69",
                "node_id": "f_76",
                "arrival_time": 8724.065991481522,
                "departure_time": 8725.065991481522,
                "current_cost": 6444.490583236516,
                "current_load": 3,
                "distance_travelled": 6444.490583236516,
                "ongoing_request": [
                    "request_69"
                ]
            },
            {
                "node": "delivery_request_69",
                "node_id": "truck_3",
                "arrival_time": 8800.25242642826,
                "departure_time": 8801.25242642826,
                "current_cost": 6519.6770181832535,
                "current_load": 0,
                "distance_travelled": 6519.6770181832535,
                "ongoing_request": []
            },
            {
                "node": "pickup_request_70",
                "node_id": "f_61",
                "arrival_time": 8874.641798955896,
                "departure_time": 8875.641798955896,
                "current_cost": 6593.066390710888,
                "current_load": 3,
                "distance_travelled": 6593.066390710888,
                "ongoing_request": [
                    "request_70"
                ]
            },
            {
                "node": "delivery_request_70",
                "node_id": "truck_2",
                "arrival_time": 8900.880657884143,
                "departure_time": 8906.008177726382,
                "current_cost": 6618.3052496391365,
                "current_load": 0,
                "distance_travelled": 6618.3052496391365,
                "ongoing_request": []
            },
            {
                "node": "pickup_request_71",
                "node_id": "f_23",
                "arrival_time": 8964.188930557537,
                "departure_time": 8965.188930557537,
                "current_cost": 6676.486002470292,
                "current_load": 3,
                "distance_travelled": 6676.486002470292,
                "ongoing_request": [
                    "request_71"
                ]
            },
            {
                "node": "delivery_request_71",
                "node_id": "truck_0",
                "arrival_time": 9067.814463442877,
                "departure_time": 9068.814463442877,
                "current_cost": 6779.111535355632,
                "current_load": 0,
                "distance_travelled": 6779.111535355632,
                "ongoing_request": []
            },
            {
                "node": "pickup_request_72",
                "node_id": "f_33",
                "arrival_time": 9119.063841548481,
                "departure_time": 9120.063841548481,
                "current_cost": 6829.360913461237,
                "current_load": 3,
                "distance_travelled": 6829.360913461237,
                "ongoing_request": [
                    "request_72"
                ]
            },
            {
                "node": "delivery_request_72",
                "node_id": "truck_0",
                "arrival_time": 9170.313219654085,
                "departure_time": 9171.313219654085,
                "current_cost": 6879.610291566842,
                "current_load": 0,
                "distance_travelled": 6879.610291566842,
                "ongoing_request": []
            },
            {
                "node": "pickup_request_73",
                "node_id": "f_17",
                "arrival_time": 9263.968494733273,
                "departure_time": 9264.968494733273,
                "current_cost": 6972.26556664603,
                "current_load": 3,
                "distance_travelled": 6972.26556664603,
                "ongoing_request": [
                    "request_73"
                ]
            },
            {
                "node": "delivery_request_73",
                "node_id": "truck_2",
                "arrival_time": 9327.258140742862,
                "departure_time": 9328.258140742862,
                "current_cost": 7034.5552126556195,
                "current_load": 0,
                "distance_travelled": 7034.5552126556195,
                "ongoing_request": []
            },
            {
                "node": "pickup_request_74",
                "node_id": "f_45",
                "arrival_time": 9378.4178855588,
                "departure_time": 9379.4178855588,
                "current_cost": 7084.714957471558,
                "current_load": 3,
                "distance_travelled": 7084.714957471558,
                "ongoing_request": [
                    "request_74"
                ]
            },
            {
                "node": "delivery_request_74",
                "node_id": "truck_2",
                "arrival_time": 9429.577630374737,
                "departure_time": 9430.577630374737,
                "current_cost": 7134.874702287496,
                "current_load": 0,
                "distance_travelled": 7134.874702287496,
                "ongoing_request": []
            },
            {
                "node": "pickup_request_75",
                "node_id": "f_4",
                "arrival_time": 9502.757960105211,
                "departure_time": 9503.757960105211,
                "current_cost": 7207.05503201797,
                "current_load": 3,
                "distance_travelled": 7207.05503201797,
                "ongoing_request": [
                    "request_75"
                ]
            },
            {
                "node": "delivery_request_75",
                "node_id": "truck_2",
                "arrival_time": 9575.938289835685,
                "departure_time": 9576.938289835685,
                "current_cost": 7279.235361748444,
                "current_load": 0,
                "distance_travelled": 7279.235361748444,
                "ongoing_request": []
            },
            {
                "node": "pickup_request_76",
                "node_id": "f_69",
                "arrival_time": 9594.630095848639,
                "departure_time": 9595.630095848639,
                "current_cost": 7296.927167761398,
                "current_load": 3,
                "distance_travelled": 7296.927167761398,
                "ongoing_request": [
                    "request_76"
                ]
            },
            {
                "node": "delivery_request_76",
                "node_id": "truck_3",
                "arrival_time": 9675.027828813756,
                "departure_time": 9676.027828813756,
                "current_cost": 7376.324900726515,
                "current_load": 0,
                "distance_travelled": 7376.324900726515,
                "ongoing_request": []
            },
            {
                "node": "pickup_request_77",
                "node_id": "f_89",
                "arrival_time": 9723.567286109776,
                "departure_time": 9724.567286109776,
                "current_cost": 7423.864358022533,
                "current_load": 3,
                "distance_travelled": 7423.864358022533,
                "ongoing_request": [
                    "request_77"
                ]
            },
            {
                "node": "delivery_request_77",
                "node_id": "truck_0",
                "arrival_time": 9804.078291637312,
                "departure_time": 9805.078291637312,
                "current_cost": 7503.375363550071,
                "current_load": 0,
                "distance_travelled": 7503.375363550071,
                "ongoing_request": []
            },
            {
                "node": "pickup_request_78",
                "node_id": "f_95",
                "arrival_time": 9867.664232550587,
                "departure_time": 9868.664232550587,
                "current_cost": 7565.961304463346,
                "current_load": 3,
                "distance_travelled": 7565.961304463346,
                "ongoing_request": [
                    "request_78"
                ]
            },
            {
                "node": "delivery_request_78",
                "node_id": "truck_0",
                "arrival_time": 9931.250173463863,
                "departure_time": 10087.236715113619,
                "current_cost": 7628.5472453766215,
                "current_load": 0,
                "distance_travelled": 7628.5472453766215,
                "ongoing_request": []
            },
            {
                "node": "pickup_request_80",
                "node_id": "f_95",
                "arrival_time": 10149.822656026894,
                "departure_time": 10150.822656026894,
                "current_cost": 7691.133186289897,
                "current_load": 3,
                "distance_travelled": 7691.133186289897,
                "ongoing_request": [
                    "request_80"
                ]
            },
            {
                "node": "delivery_request_80",
                "node_id": "truck_0",
                "arrival_time": 10213.40859694017,
                "departure_time": 10389.774380364992,
                "current_cost": 7753.719127203172,
                "current_load": 0,
                "distance_travelled": 7753.719127203172,
                "ongoing_request": []
            },
            {
                "node": "pickup_request_82",
                "node_id": "f_28",
                "arrival_time": 10430.786573673811,
                "departure_time": 10431.786573673811,
                "current_cost": 7794.731320511992,
                "current_load": 3,
                "distance_travelled": 7794.731320511992,
                "ongoing_request": [
                    "request_82"
                ]
            },
            {
                "node": "delivery_request_82",
                "node_id": "truck_0",
                "arrival_time": 10472.79876698263,
                "departure_time": 10516.566105841583,
                "current_cost": 7835.743513820811,
                "current_load": 0,
                "distance_travelled": 7835.743513820811,
                "ongoing_request": []
            },
            {
                "node": "pickup_request_83",
                "node_id": "f_96",
                "arrival_time": 10552.966655287984,
                "departure_time": 10553.966655287984,
                "current_cost": 7872.144063267214,
                "current_load": 3,
                "distance_travelled": 7872.144063267214,
                "ongoing_request": [
                    "request_83"
                ]
            },
            {
                "node": "delivery_request_83",
                "node_id": "truck_3",
                "arrival_time": 10642.357831318173,
                "departure_time": 10680.405532434736,
                "current_cost": 7960.535239297404,
                "current_load": 0,
                "distance_travelled": 7960.535239297404,
                "ongoing_request": []
            },
            {
                "node": "pickup_request_84",
                "node_id": "f_77",
                "arrival_time": 10761.325245731312,
                "departure_time": 10762.325245731312,
                "current_cost": 8041.454952593979,
                "current_load": 3,
                "distance_travelled": 8041.454952593979,
                "ongoing_request": [
                    "request_84"
                ]
            },
            {
                "node": "delivery_request_84",
                "node_id": "truck_3",
                "arrival_time": 10843.244959027888,
                "departure_time": 10873.416967466901,
                "current_cost": 8122.374665890555,
                "current_load": 0,
                "distance_travelled": 8122.374665890555,
                "ongoing_request": []
            },
            {
                "node": "pickup_request_86",
                "node_id": "f_94",
                "arrival_time": 10940.327355300182,
                "departure_time": 10941.327355300182,
                "current_cost": 8189.2850537238355,
                "current_load": 3,
                "distance_travelled": 8189.2850537238355,
                "ongoing_request": [
                    "request_86"
                ]
            },
            {
                "node": "delivery_request_86",
                "node_id": "truck_2",
                "arrival_time": 10974.613989254369,
                "departure_time": 10975.613989254369,
                "current_cost": 8222.571687678022,
                "current_load": 0,
                "distance_travelled": 8222.571687678022,
                "ongoing_request": []
            },
            {
                "node": "pickup_request_87",
                "node_id": "f_62",
                "arrival_time": 11000.673917426651,
                "departure_time": 11001.673917426651,
                "current_cost": 8247.631615850305,
                "current_load": 3,
                "distance_travelled": 8247.631615850305,
                "ongoing_request": [
                    "request_87"
                ]
            },
            {
                "node": "delivery_request_87",
                "node_id": "truck_3",
                "arrival_time": 11072.50470169451,
                "departure_time": 11103.904331152546,
                "current_cost": 8318.462400118164,
                "current_load": 0,
                "distance_travelled": 8318.462400118164,
                "ongoing_request": []
            },
            {
                "node": "pickup_request_88",
                "node_id": "f_81",
                "arrival_time": 11167.43385184962,
                "departure_time": 11168.43385184962,
                "current_cost": 8381.991920815239,
                "current_load": 3,
                "distance_travelled": 8381.991920815239,
                "ongoing_request": [
                    "request_88"
                ]
            },
            {
                "node": "delivery_request_88",
                "node_id": "truck_0",
                "arrival_time": 11235.500982398049,
                "departure_time": 11236.500982398049,
                "current_cost": 8449.059051363667,
                "current_load": 0,
                "distance_travelled": 8449.059051363667,
                "ongoing_request": []
            },
            {
                "node": "pickup_request_89",
                "node_id": "f_29",
                "arrival_time": 11322.622988877229,
                "departure_time": 11323.622988877229,
                "current_cost": 8535.181057842847,
                "current_load": 3,
                "distance_travelled": 8535.181057842847,
                "ongoing_request": [
                    "request_89"
                ]
            },
            {
                "node": "delivery_request_89",
                "node_id": "truck_2",
                "arrival_time": 11353.152634997696,
                "departure_time": 11363.89687107207,
                "current_cost": 8564.710703963314,
                "current_load": 0,
                "distance_travelled": 8564.710703963314,
                "ongoing_request": []
            },
            {
                "node": "pickup_request_90",
                "node_id": "f_19",
                "arrival_time": 11412.558971314455,
                "departure_time": 11413.558971314455,
                "current_cost": 8613.3728042057,
                "current_load": 3,
                "distance_travelled": 8613.3728042057,
                "ongoing_request": [
                    "request_90"
                ]
            },
            {
                "node": "delivery_request_90",
                "node_id": "truck_1",
                "arrival_time": 11505.237758391946,
                "departure_time": 11506.237758391946,
                "current_cost": 8705.05159128319,
                "current_load": 0,
                "distance_travelled": 8705.05159128319,
                "ongoing_request": []
            },
            {
                "node": "pickup_request_91",
                "node_id": "f_44",
                "arrival_time": 11542.638307838348,
                "departure_time": 11543.638307838348,
                "current_cost": 8741.452140729592,
                "current_load": 3,
                "distance_travelled": 8741.452140729592,
                "ongoing_request": [
                    "request_91"
                ]
            },
            {
                "node": "delivery_request_91",
                "node_id": "truck_3",
                "arrival_time": 11625.179708365933,
                "departure_time": 11711.067593630733,
                "current_cost": 8822.993541257178,
                "current_load": 0,
                "distance_travelled": 8822.993541257178,
                "ongoing_request": []
            },
            {
                "node": "pickup_request_92",
                "node_id": "f_13",
                "arrival_time": 11823.68197992307,
                "departure_time": 11824.68197992307,
                "current_cost": 8935.607927549516,
                "current_load": 3,
                "distance_travelled": 8935.607927549516,
                "ongoing_request": [
                    "request_92"
                ]
            },
            {
                "node": "pickup_request_93",
                "node_id": "f_38",
                "arrival_time": 11918.942257877254,
                "departure_time": 11919.942257877254,
                "current_cost": 9029.868205503699,
                "current_load": 6,
                "distance_travelled": 9029.868205503699,
                "ongoing_request": [
                    "request_92",
                    "request_93"
                ]
            },
            {
                "node": "delivery_request_92",
                "node_id": "truck_3",
                "arrival_time": 11947.016230618616,
                "departure_time": 11948.016230618616,
                "current_cost": 9056.94217824506,
                "current_load": 3,
                "distance_travelled": 9056.94217824506,
                "ongoing_request": [
                    "request_93"
                ]
            },
            {
                "node": "delivery_request_93",
                "node_id": "truck_1",
                "arrival_time": 12011.687048108402,
                "departure_time": 12012.687048108402,
                "current_cost": 9120.612995734848,
                "current_load": 0,
                "distance_travelled": 9120.612995734848,
                "ongoing_request": []
            },
            {
                "node": "pickup_request_95",
                "node_id": "f_33",
                "arrival_time": 12102.31405296743,
                "departure_time": 12103.31405296743,
                "current_cost": 9210.240000593874,
                "current_load": 3,
                "distance_travelled": 9210.240000593874,
                "ongoing_request": [
                    "request_95"
                ]
            },
            {
                "node": "delivery_request_95",
                "node_id": "truck_0",
                "arrival_time": 12153.563431073033,
                "departure_time": 12154.563431073033,
                "current_cost": 9260.489378699478,
                "current_load": 0,
                "distance_travelled": 9260.489378699478,
                "ongoing_request": []
            },
            {
                "node": "pickup_request_94",
                "node_id": "f_96",
                "arrival_time": 12190.963980519435,
                "departure_time": 12191.963980519435,
                "current_cost": 9296.88992814588,
                "current_load": 3,
                "distance_travelled": 9296.88992814588,
                "ongoing_request": [
                    "request_94"
                ]
            },
            {
                "node": "pickup_request_96",
                "node_id": "f_0",
                "arrival_time": 12257.217332923736,
                "departure_time": 12258.217332923736,
                "current_cost": 9362.14328055018,
                "current_load": 6,
                "distance_travelled": 9362.14328055018,
                "ongoing_request": [
                    "request_94",
                    "request_96"
                ]
            },
            {
                "node": "delivery_request_96",
                "node_id": "truck_0",
                "arrival_time": 12314.190540800362,
                "departure_time": 12315.190540800362,
                "current_cost": 9418.116488426807,
                "current_load": 3,
                "distance_travelled": 9418.116488426807,
                "ongoing_request": [
                    "request_94"
                ]
            },
            {
                "node": "pickup_request_97",
                "node_id": "f_4",
                "arrival_time": 12369.421528252187,
                "departure_time": 12370.421528252187,
                "current_cost": 9472.347475878632,
                "current_load": 6,
                "distance_travelled": 9472.347475878632,
                "ongoing_request": [
                    "request_94",
                    "request_97"
                ]
            },
            {
                "node": "delivery_request_94",
                "node_id": "truck_2",
                "arrival_time": 12442.601857982661,
                "departure_time": 12443.601857982661,
                "current_cost": 9544.527805609107,
                "current_load": 3,
                "distance_travelled": 9544.527805609107,
                "ongoing_request": [
                    "request_97"
                ]
            },
            {
                "node": "delivery_request_97",
                "node_id": "truck_2",
                "arrival_time": 12443.601857982661,
                "departure_time": 12444.601857982661,
                "current_cost": 9544.527805609107,
                "current_load": 0,
                "distance_travelled": 9544.527805609107,
                "ongoing_request": []
            },
            {
                "node": "pickup_request_98",
                "node_id": "f_16",
                "arrival_time": 12465.21738611075,
                "departure_time": 12466.21738611075,
                "current_cost": 9565.143333737195,
                "current_load": 3,
                "distance_travelled": 9565.143333737195,
                "ongoing_request": [
                    "request_98"
                ]
            },
            {
                "node": "delivery_request_98",
                "node_id": "truck_1",
                "arrival_time": 12523.226157365707,
                "departure_time": 12524.226157365707,
                "current_cost": 9622.152104992152,
                "current_load": 0,
                "distance_travelled": 9622.152104992152,
                "ongoing_request": []
            },
            {
                "node": "pickup_request_100",
                "node_id": "f_36",
                "arrival_time": 12560.626706812109,
                "departure_time": 12561.626706812109,
                "current_cost": 9658.552654438554,
                "current_load": 3,
                "distance_travelled": 9658.552654438554,
                "ongoing_request": [
                    "request_100"
                ]
            },
            {
                "node": "delivery_request_100",
                "node_id": "truck_2",
                "arrival_time": 12599.574038734128,
                "departure_time": 12600.574038734128,
                "current_cost": 9696.499986360574,
                "current_load": 0,
                "distance_travelled": 9696.499986360574,
                "ongoing_request": []
            },
            {
                "node": "pickup_request_99",
                "node_id": "f_78",
                "arrival_time": 12636.042334436064,
                "departure_time": 12637.042334436064,
                "current_cost": 9731.96828206251,
                "current_load": 3,
                "distance_travelled": 9731.96828206251,
                "ongoing_request": [
                    "request_99"
                ]
            },
            {
                "node": "delivery_request_99",
                "node_id": "truck_3",
                "arrival_time": 12672.552896245194,
                "departure_time": 12886.899765671866,
                "current_cost": 9767.478843871639,
                "current_load": 0,
                "distance_travelled": 9767.478843871639,
                "ongoing_request": []
            },
            {
                "node": "end_robot_5",
                "node_id": "depot_0",
                "arrival_time": 12937.622658567143,
                "departure_time": 12937.622658567143,
                "current_cost": 9818.201736766916,
                "current_load": 0,
                "distance_travelled": 9818.201736766916,
                "ongoing_request": []
            }
        ],
        "robot_6": [
            {
                "node": "start_robot_6",
                "node_id": "depot_1",
                "arrival_time": 0.0,
                "departure_time": 12937.622658567143,
                "current_cost": 0.0,
                "current_load": 0,
                "distance_travelled": 0.0,
                "ongoing_request": []
            },
            {
                "node": "end_robot_6",
                "node_id": "depot_1",
                "arrival_time": 12937.622658567143,
                "departure_time": 12937.622658567143,
                "current_cost": 0.0,
                "current_load": 0,
                "distance_travelled": 0.0,
                "ongoing_request": []
            }
        ],
        "robot_7": [
            {
                "node": "start_robot_7",
                "node_id": "depot_3",
                "arrival_time": 0.0,
                "departure_time": 12937.622658567143,
                "current_cost": 0.0,
                "current_load": 0,
                "distance_travelled": 0.0,
                "ongoing_request": []
            },
            {
                "node": "end_robot_7",
                "node_id": "depot_3",
                "arrival_time": 12937.622658567143,
                "departure_time": 12937.622658567143,
                "current_cost": 0.0,
                "current_load": 0,
                "distance_travelled": 0.0,
                "ongoing_request": []
            }
        ],
        "robot_8": [
            {
                "node": "start_robot_8",
                "node_id": "depot_3",
                "arrival_time": 0.0,
                "departure_time": 12937.622658567143,
                "current_cost": 0.0,
                "current_load": 0,
                "distance_travelled": 0.0,
                "ongoing_request": []
            },
            {
                "node": "end_robot_8",
                "node_id": "depot_3",
                "arrival_time": 12937.622658567143,
                "departure_time": 12937.622658567143,
                "current_cost": 0.0,
                "current_load": 0,
                "distance_travelled": 0.0,
                "ongoing_request": []
            }
        ],
        "robot_9": [
            {
                "node": "start_robot_9",
                "node_id": "depot_3",
                "arrival_time": 0.0,
                "departure_time": 0.0,
                "current_cost": 0.0,
                "current_load": 0,
                "distance_travelled": 0.0,
                "ongoing_request": []
            },
            {
                "node": "pickup_request_1",
                "node_id": "f_23",
                "arrival_time": 3.1622776601683795,
                "departure_time": 4.162277660168385,
                "current_cost": 3.1622776601683795,
                "current_load": 3,
                "distance_travelled": 3.1622776601683795,
                "ongoing_request": [
                    "request_1"
                ]
            },
            {
                "node": "delivery_request_1",
                "node_id": "truck_1",
                "arrival_time": 70.44953133687459,
                "departure_time": 83.53067410977846,
                "current_cost": 69.44953133687459,
                "current_load": 0,
                "distance_travelled": 69.44953133687459,
                "ongoing_request": []
            },
            {
                "node": "pickup_request_2",
                "node_id": "f_10",
                "arrival_time": 114.9153837627289,
                "departure_time": 115.91538376272891,
                "current_cost": 100.83424098982502,
                "current_load": 3,
                "distance_travelled": 100.83424098982502,
                "ongoing_request": [
                    "request_2"
                ]
            },
            {
                "node": "delivery_request_2",
                "node_id": "truck_0",
                "arrival_time": 185.97963998514234,
                "departure_time": 196.30543452282208,
                "current_cost": 170.89849721223845,
                "current_load": 0,
                "distance_travelled": 170.89849721223845,
                "ongoing_request": []
            },
            {
                "node": "pickup_request_3",
                "node_id": "f_39",
                "arrival_time": 256.51340741678354,
                "departure_time": 257.51340741678354,
                "current_cost": 231.10647010619994,
                "current_load": 3,
                "distance_travelled": 231.10647010619994,
                "ongoing_request": [
                    "request_3"
                ]
            },
            {
                "node": "delivery_request_3",
                "node_id": "truck_3",
                "arrival_time": 308.0801949358657,
                "departure_time": 1500.4485320701167,
                "current_cost": 281.6732576252821,
                "current_load": 0,
                "distance_travelled": 281.6732576252821,
                "ongoing_request": []
            },
            {
                "node": "pickup_request_14",
                "node_id": "f_10",
                "arrival_time": 1557.2728226508182,
                "departure_time": 1558.2728226508182,
                "current_cost": 338.49754820598355,
                "current_load": 3,
                "distance_travelled": 338.49754820598355,
                "ongoing_request": [
                    "request_14"
                ]
            },
            {
                "node": "delivery_request_14",
                "node_id": "truck_3",
                "arrival_time": 1615.0971132315196,
                "departure_time": 1825.4474458524085,
                "current_cost": 395.321838786685,
                "current_load": 0,
                "distance_travelled": 395.321838786685,
                "ongoing_request": []
            },
            {
                "node": "pickup_request_17",
                "node_id": "f_82",
                "arrival_time": 1898.4542948461844,
                "departure_time": 1899.4542948461844,
                "current_cost": 468.32868778046094,
                "current_load": 3,
                "distance_travelled": 468.32868778046094,
                "ongoing_request": [
                    "request_17"
                ]
            },
            {
                "node": "delivery_request_17",
                "node_id": "truck_3",
                "arrival_time": 1972.4611438399604,
                "departure_time": 2999.4154308079046,
                "current_cost": 541.3355367742369,
                "current_load": 0,
                "distance_travelled": 541.3355367742369,
                "ongoing_request": []
            },
            {
                "node": "pickup_request_26",
                "node_id": "f_8",
                "arrival_time": 3010.5957706954036,
                "departure_time": 3011.5957706954036,
                "current_cost": 552.5158766617358,
                "current_load": 3,
                "distance_travelled": 552.5158766617358,
                "ongoing_request": [
                    "request_26"
                ]
            },
            {
                "node": "delivery_request_26",
                "node_id": "truck_3",
                "arrival_time": 3022.7761105829027,
                "departure_time": 4008.3065680832656,
                "current_cost": 563.6962165492347,
                "current_load": 0,
                "distance_travelled": 563.6962165492347,
                "ongoing_request": []
            },
            {
                "node": "pickup_request_32",
                "node_id": "f_8",
                "arrival_time": 4019.4869079707646,
                "departure_time": 4020.486907970765,
                "current_cost": 574.8765564367336,
                "current_load": 3,
                "distance_travelled": 574.8765564367336,
                "ongoing_request": [
                    "request_32"
                ]
            },
            {
                "node": "delivery_request_32",
                "node_id": "truck_0",
                "arrival_time": 4135.033841583149,
                "departure_time": 4164.423406877732,
                "current_cost": 689.423490049118,
                "current_load": 0,
                "distance_travelled": 689.423490049118,
                "ongoing_request": []
            },
            {
                "node": "pickup_request_33",
                "node_id": "f_93",
                "arrival_time": 4241.481826274966,
                "departure_time": 4242.481826274966,
                "current_cost": 766.4819094463519,
                "current_load": 3,
                "distance_travelled": 766.4819094463519,
                "ongoing_request": [
                    "request_33"
                ]
            },
            {
                "node": "delivery_request_33",
                "node_id": "truck_0",
                "arrival_time": 4319.5402456721995,
                "departure_time": 4320.5402456721995,
                "current_cost": 843.5403288435858,
                "current_load": 0,
                "distance_travelled": 843.5403288435858,
                "ongoing_request": []
            },
            {
                "node": "pickup_request_34",
                "node_id": "f_86",
                "arrival_time": 4335.5735420505725,
                "departure_time": 4336.5735420505725,
                "current_cost": 858.5736252219588,
                "current_load": 3,
                "distance_travelled": 858.5736252219588,
                "ongoing_request": [
                    "request_34"
                ]
            },
            {
                "node": "delivery_request_34",
                "node_id": "truck_3",
                "arrival_time": 4454.2170714093945,
                "departure_time": 4821.711576933977,
                "current_cost": 976.2171545807807,
                "current_load": 0,
                "distance_travelled": 976.2171545807807,
                "ongoing_request": []
            },
            {
                "node": "pickup_request_37",
                "node_id": "f_90",
                "arrival_time": 4899.737213746502,
                "departure_time": 4900.737213746502,
                "current_cost": 1054.2427913933054,
                "current_load": 3,
                "distance_travelled": 1054.2427913933054,
                "ongoing_request": [
                    "request_37"
                ]
            },
            {
                "node": "delivery_request_37",
                "node_id": "truck_3",
                "arrival_time": 4978.762850559026,
                "departure_time": 6684.557984851492,
                "current_cost": 1132.26842820583,
                "current_load": 0,
                "distance_travelled": 1132.26842820583,
                "ongoing_request": []
            },
            {
                "node": "pickup_request_53",
                "node_id": "f_47",
                "arrival_time": 6763.867505087085,
                "departure_time": 6764.867505087085,
                "current_cost": 1211.5779484414236,
                "current_load": 3,
                "distance_travelled": 1211.5779484414236,
                "ongoing_request": [
                    "request_53"
                ]
            },
            {
                "node": "delivery_request_53",
                "node_id": "truck_3",
                "arrival_time": 6844.177025322679,
                "departure_time": 7586.897155321535,
                "current_cost": 1290.887468677017,
                "current_load": 0,
                "distance_travelled": 1290.887468677017,
                "ongoing_request": []
            },
            {
                "node": "pickup_request_61",
                "node_id": "f_35",
                "arrival_time": 7656.961411543949,
                "departure_time": 7657.961411543949,
                "current_cost": 1360.9517248994305,
                "current_load": 3,
                "distance_travelled": 1360.9517248994305,
                "ongoing_request": [
                    "request_61"
                ]
            },
            {
                "node": "delivery_request_61",
                "node_id": "truck_3",
                "arrival_time": 7728.025667766363,
                "departure_time": 8010.828352662891,
                "current_cost": 1431.0159811218439,
                "current_load": 0,
                "distance_travelled": 1431.0159811218439,
                "ongoing_request": []
            },
            {
                "node": "pickup_request_64",
                "node_id": "f_55",
                "arrival_time": 8108.080601994205,
                "departure_time": 8109.080601994205,
                "current_cost": 1528.2682304531575,
                "current_load": 3,
                "distance_travelled": 1528.2682304531575,
                "ongoing_request": [
                    "request_64"
                ]
            },
            {
                "node": "delivery_request_64",
                "node_id": "truck_3",
                "arrival_time": 8206.332851325518,
                "departure_time": 9946.591586721117,
                "current_cost": 1625.520479784471,
                "current_load": 0,
                "distance_travelled": 1625.520479784471,
                "ongoing_request": []
            },
            {
                "node": "pickup_request_79",
                "node_id": "f_73",
                "arrival_time": 10029.084010615677,
                "departure_time": 10030.084010615677,
                "current_cost": 1708.0129036790324,
                "current_load": 3,
                "distance_travelled": 1708.0129036790324,
                "ongoing_request": [
                    "request_79"
                ]
            },
            {
                "node": "delivery_request_79",
                "node_id": "truck_3",
                "arrival_time": 10112.576434510238,
                "departure_time": 10268.967585701066,
                "current_cost": 1790.5053275735938,
                "current_load": 0,
                "distance_travelled": 1790.5053275735938,
                "ongoing_request": []
            },
            {
                "node": "pickup_request_81",
                "node_id": "f_1",
                "arrival_time": 10348.973835456945,
                "departure_time": 10349.973835456945,
                "current_cost": 1870.5115773294722,
                "current_load": 3,
                "distance_travelled": 1870.5115773294722,
                "ongoing_request": [
                    "request_81"
                ]
            },
            {
                "node": "delivery_request_81",
                "node_id": "truck_3",
                "arrival_time": 10429.980085212825,
                "departure_time": 10771.219945679433,
                "current_cost": 1950.5178270853505,
                "current_load": 0,
                "distance_travelled": 1950.5178270853505,
                "ongoing_request": []
            },
            {
                "node": "pickup_request_85",
                "node_id": "f_41",
                "arrival_time": 10815.627152301782,
                "departure_time": 10816.627152301782,
                "current_cost": 1994.9250337076996,
                "current_load": 3,
                "distance_travelled": 1994.9250337076996,
                "ongoing_request": [
                    "request_85"
                ]
            },
            {
                "node": "delivery_request_85",
                "node_id": "truck_3",
                "arrival_time": 10861.034358924131,
                "departure_time": 12927.965804317651,
                "current_cost": 2039.3322403300488,
                "current_load": 0,
                "distance_travelled": 2039.3322403300488,
                "ongoing_request": []
            },
            {
                "node": "end_robot_9",
                "node_id": "depot_3",
                "arrival_time": 12937.622658567143,
                "departure_time": 12937.622658567143,
                "current_cost": 2048.989094579541,
                "current_load": 0,
                "distance_travelled": 2048.989094579541,
                "ongoing_request": []
            }
        ],
        "extra_robot_1": [
            {
                "node": "start_extra_robot_1",
                "node_id": "depot_0",
                "arrival_time": 0.0,
                "departure_time": 12937.622658567143,
                "current_cost": 0.0,
                "current_load": 0,
                "distance_travelled": 0.0,
                "ongoing_request": []
            },
            {
                "node": "end_extra_robot_1",
                "node_id": "depot_0",
                "arrival_time": 12937.622658567143,
                "departure_time": 12937.622658567143,
                "current_cost": 0.0,
                "current_load": 0,
                "distance_travelled": 0.0,
                "ongoing_request": []
            }
        ]
    },
    "iteration_cost": [
        146,
        286,
        301,
        454,
        614,
        664,
        734,
        786,
        864,
        984,
        1131,
        1246,
        1423,
        1537,
        1715,
        1767,
        1913,
        2027,
        2156,
        2352,
        2453,
        2561,
        2677,
        2814,
        2920,
        2943,
        3054,
        3212,
        3322,
        3498,
        3646,
        3868,
        4022,
        4059,
        4190,
        4368,
        4524,
        4560,
        4649,
        4846,
        4969,
        5013,
        5120,
        5159,
        5307,
        5408,
        5542,
        5679,
        5863,
        6005,
        6150,
        6165,
        6323,
        6469,
        6576,
        6694,
        6742,
        6796,
        6957,
        7045,
        7185,
        7306,
        7409,
        7603,
        7705,
        7824,
        7945,
        8078,
        8225,
        8297,
        8494,
        8594,
        8713,
        8813,
        8957,
        9082,
        9218,
        9343,
        9508,
        9633,
        9793,
        9875,
        9991,
        10153,
        10242,
        10315,
        10438,
        10577,
        10657,
        10833,
        10942,
        11167,
        11248,
        11304,
        11416,
        11568,
        11637,
        11750,
        11805,
        11887
    ],
    "iteration_cost_2": [
        0,
        110,
        241,
        304,
        481,
        481,
        551,
        629,
        798,
        831,
        988,
        1062,
        1261,
        1410,
        1556,
        1646,
        1765,
        1898,
        2018,
        2191,
        2283,
        2384,
        2424,
        2607,
        2745,
        2862,
        2901,
        3063,
        3143,
        3345,
        3429,
        3588,
        3779,
        3856,
        4055,
        4210,
        4377,
        4438,
        4527,
        4690,
        4777,
        4842,
        4917,
        4997,
        5099,
        5181,
        5339,
        5473,
        5711,
        5803,
        5945,
        6023,
        6211,
        6363,
        6436,
        6516,
        6612,
        6667,
        6804,
        6888,
        7055,
        7129,
        7265,
        7446,
        7621,
        7672,
        7818,
        7885,
        8090,
        8165,
        8322,
        8424,
        8525,
        8680,
        8780,
        8924,
        9021,
        9148,
        9356,
        9501,
        9644,
        9765,
        9842,
        10011,
        10137,
        10248,
        10281,
        10441,
        10508,
        10672,
        10764,
        10994,
        10994,
        11089,
        11179,
        11319,
        11421,
        11531,
        11603,
        11681,
        11887
    ],
    "computational_time": 0.8304660320281982
}